unstract/llmwhisperer/__init__.py
unstract/llmwhisperer/client_v2.py
unstract/llmwhisperer/utils.py
llmwhisperer_client-2.5.0.dist-info/METADATA
llmwhisperer_client-2.5.0.dist-info/WHEEL
llmwhisperer_client-2.5.0.dist-info/licenses/LICENSE
llmwhisperer_client-2.5.0.dist-info/RECORD
