Metadata-Version: 2.4
Name: llmwhisperer-client
Version: 2.5.0
Summary: Client library for LLM Whisperer
Project-URL: Homepage, https://unstract.com/llmwhisperer/
Project-URL: Source, https://github.com/Zipstack/llm-whisperer-python-client
Author-email: Zipstack Inc <devsupport@zipstack.com>
License: AGPL v3
License-File: LICENSE
Keywords: llmwhisperer tools-development-kit apps development-kit sdk
Classifier: Development Status :: 4 - Beta
Classifier: Intended Audience :: Developers
Classifier: License :: OSI Approved :: GNU Affero General Public License v3
Classifier: Operating System :: MacOS :: MacOS X
Classifier: Operating System :: Microsoft :: Windows
Classifier: Operating System :: POSIX :: Linux
Classifier: Programming Language :: Python
Classifier: Topic :: Software Development :: Libraries :: Python Modules
Requires-Python: >=3.12
Requires-Dist: requests>=2
